__init__.py
src/__init__.py
src/copy_of_merck.py
src/BABERT_wardcheyenne/__init__.py
mbabert-0.0.3.dist-info/METADATA
mbabert-0.0.3.dist-info/WHEEL
mbabert-0.0.3.dist-info/RECORD
