Metadata-Version: 2.1
Name: MBABERT
Version: 0.0.3
Summary: A BERT Model trained on Pubmed Copora.
Author-email: Cheyenne Ward <wardlcheyenne@gmail.com>
Classifier: License :: OSI Approved :: MIT License
Classifier: Operating System :: OS Independent
Classifier: Programming Language :: Python :: 3
Requires-Python: >=3.7
